autotorrent/__init__.py
autotorrent/__main__.py
autotorrent/__version__.py
autotorrent/db.py
autotorrent/exceptions.py
autotorrent/indexer.py
autotorrent/matcher.py
autotorrent/rw_cache.py
autotorrent/utils.py
autotorrent2-1.3.0.dist-info/LICENSE
autotorrent2-1.3.0.dist-info/METADATA
autotorrent2-1.3.0.dist-info/WHEEL
autotorrent2-1.3.0.dist-info/entry_points.txt
autotorrent2-1.3.0.dist-info/top_level.txt
autotorrent2-1.3.0.dist-info/RECORD
