Metadata-Version: 2.1
Name: autotorrent2
Version: 1.3.0
Summary: Torrent lifecycle management tool
Home-page: https://github.com/johndoee/autotorrent2
Author: John
Classifier: Programming Language :: Python :: 3
Classifier: License :: OSI Approved :: MIT License
Classifier: Operating System :: OS Independent
Requires-Python: >=3.7
License-File: LICENSE
Requires-Dist: libtc <2,>=1.3.4
Requires-Dist: toml <0.10.99,>=0.10.1
Requires-Dist: appdirs <2,>=1.4.4
Requires-Dist: click <9,>=8.0.0
Requires-Dist: chardet <5,>=4.0.0
Provides-Extra: docs
Requires-Dist: mkdocs ==1.3.0 ; extra == 'docs'
Requires-Dist: mkdocs-click ==0.7.0 ; extra == 'docs'
Provides-Extra: test
Requires-Dist: pytest >=6.0.1 ; extra == 'test'
